altwalker_viewer/__init__.py
altwalker_viewer/__main__.py
altwalker_viewer/__version__.py
altwalker_viewer/cli.py
altwalker_viewer/client.py
altwalker_viewer/reporter.py
altwalker_viewer/server.py
altwalker_viewer/status.py
altwalker_viewer/walker.py
altwalker_viewer/dist/15c8420b0e6e542a978f.svg
altwalker_viewer/dist/68659bacae74b54ea28c.svg
altwalker_viewer/dist/c60ee78200e01104d302.svg
altwalker_viewer/dist/eb64b001bca05f6e3811.png
altwalker_viewer/dist/ec7bf1eb98b0b823dd6d.png
altwalker_viewer/dist/favicon.ico
altwalker_viewer/dist/index.html
altwalker_viewer/dist/main.css
altwalker_viewer/dist/main.js
altwalker_viewer/dist/service-worker.js
altwalker_viewer/dist/workbox-1c3383c2.js
tests/__init__.py
tests/integration/__init__.py
tests/integration/test_server.py
tests/unit/__init__.py
tests/unit/test_cli.py
altwalker_live_viewer-0.4.2.dist-info/LICENSE
altwalker_live_viewer-0.4.2.dist-info/METADATA
altwalker_live_viewer-0.4.2.dist-info/WHEEL
altwalker_live_viewer-0.4.2.dist-info/entry_points.txt
altwalker_live_viewer-0.4.2.dist-info/top_level.txt
altwalker_live_viewer-0.4.2.dist-info/RECORD
