Metadata-Version: 2.1
Name: altwalker-live-viewer
Version: 0.4.2
Summary: A web application for visualizing the progress of an AltWalker test run.
Author-email: Altom Consulting <altwalker@altom.com>, Dezmerean Robert <dezmereanrobert@gmail.com>
License: GNU GPLv3
Project-URL: Homepage, https://github.com/altwalker/live-viewer
Project-URL: Repository, https://github.com/altwalker/live-viewer.git
Project-URL: Bug Tracker, https://github.com/altwalker/live-viewer/issues
Keywords: model-based-testing,testing,tests,testing-framework
Classifier: Development Status :: 4 - Beta
Classifier: Development Status :: 5 - Production/Stable
Classifier: Intended Audience :: Developers
Classifier: Intended Audience :: Other Audience
Classifier: Environment :: Console
Classifier: License :: OSI Approved :: GNU General Public License v3 (GPLv3)
Classifier: Programming Language :: C#
Classifier: Programming Language :: Cython
Classifier: Programming Language :: Python :: Implementation
Classifier: Programming Language :: Python :: Implementation :: CPython
Classifier: Programming Language :: Python :: Implementation :: PyPy
Classifier: Programming Language :: Python :: 3 :: Only
Classifier: Programming Language :: Python :: 3.8
Classifier: Programming Language :: Python :: 3.9
Classifier: Programming Language :: Python :: 3.10
Classifier: Programming Language :: Python :: 3.11
Classifier: Operating System :: OS Independent
Classifier: Topic :: Software Development :: Libraries
Classifier: Topic :: Software Development :: Testing
Classifier: Topic :: Software Development :: Testing :: Acceptance
Requires-Python: >=3.8
License-File: LICENSE
Requires-Dist: altwalker >=0.4.0
Requires-Dist: websockets
Requires-Dist: requests
Provides-Extra: debug
Requires-Dist: rich ; extra == 'debug'
